lion/__init__.py
lion/conditions.py
lion/contrib/__init__.py
lion/contrib/drf.py
lion/fields.py
lion/getters.py
lion/mapper.py
lion/ql.py
lion/update.py
lion-0.4.1.dist-info/LICENSE
lion-0.4.1.dist-info/WHEEL
lion-0.4.1.dist-info/METADATA
lion-0.4.1.dist-info/RECORD
