Metadata-Version: 2.1
Name: lion
Version: 0.4.1
Summary: Fast and flexible object mapping (serialization, marshalling)
Home-page: https://github.com/bikeshedder/lion
License: BSD-2-Clause
Author: Michael P. Jung
Author-email: michael.jung@terreon.de
Requires-Python: >=3.5,<4.0
Classifier: Development Status :: 4 - Beta
Classifier: Intended Audience :: Developers
Classifier: License :: OSI Approved :: BSD License
Classifier: Operating System :: OS Independent
Classifier: Programming Language :: Python
Classifier: Programming Language :: Python :: 3
Classifier: Programming Language :: Python :: 3.5
Classifier: Programming Language :: Python :: 3.6
Classifier: Programming Language :: Python :: 3.7
Classifier: Programming Language :: Python :: 3.8
Classifier: Topic :: Software Development :: Libraries :: Application Frameworks
Classifier: Topic :: Software Development :: Libraries :: Python Modules
Requires-Dist: python-dateutil (>=2.8.1,<3.0.0)
Requires-Dist: pytz (>=2020.1,<2021.0)
Project-URL: Repository, https://github.com/bikeshedder/lion
